mlflow_rest_client/VERSION
mlflow_rest_client/__init__.py
mlflow_rest_client/artifact.py
mlflow_rest_client/experiment.py
mlflow_rest_client/internal.py
mlflow_rest_client/mlflow_rest_client.py
mlflow_rest_client/model.py
mlflow_rest_client/page.py
mlflow_rest_client/run.py
mlflow_rest_client/tag.py
mlflow_rest_client/timestamp.py
mlflow_rest_client/version.py
mlflow_rest_client-2.0.0.dist-info/LICENSE.txt
mlflow_rest_client-2.0.0.dist-info/METADATA
mlflow_rest_client-2.0.0.dist-info/WHEEL
mlflow_rest_client-2.0.0.dist-info/top_level.txt
mlflow_rest_client-2.0.0.dist-info/RECORD
