Metadata-Version: 2.1
Name: mlflow-rest-client
Version: 2.0.0
Summary: Python client for MLflow REST API
Home-page: https://github.com/MobileTeleSystems/mlflow-rest-client
Author: MTS DSX Team
Author-email: dsx-team@mts.ru
License: Apache License 2.0
Project-URL: Documentation, https://mlflow-rest-client.readthedocs.io/en/stable/
Project-URL: Source, https://github.com/MobileTeleSystems/mlflow-rest-client
Project-URL: CI/CD, https://github.com/MobileTeleSystems/mlflow-rest-client/actions
Project-URL: Tracker, https://github.com/MobileTeleSystems/mlflow-rest-client/issues
Keywords: MLflow REST API
Platform: UNKNOWN
Classifier: Development Status :: 4 - Beta
Classifier: Environment :: Console
Classifier: Intended Audience :: Developers
Classifier: License :: OSI Approved :: Apache Software License
Classifier: Operating System :: OS Independent
Classifier: Programming Language :: Python :: 3 :: Only
Classifier: Programming Language :: Python :: 3.10
Classifier: Programming Language :: Python :: 3.7
Classifier: Programming Language :: Python :: 3.8
Classifier: Programming Language :: Python :: 3.9
Classifier: Programming Language :: Python :: Implementation :: CPython
Classifier: Programming Language :: Python :: Implementation :: PyPy
Classifier: Topic :: Software Development :: Libraries :: Python Modules
Classifier: Typing :: Typed
Requires-Python: >=3.7
License-File: LICENSE.txt
Requires-Dist: datetime
Requires-Dist: pydantic
Requires-Dist: requests
Requires-Dist: urllib3
